LICENCE
README.md
setup.py
biblioteca_enigma.egg-info/PKG-INFO
biblioteca_enigma.egg-info/SOURCES.txt
biblioteca_enigma.egg-info/dependency_links.txt
biblioteca_enigma.egg-info/requires.txt
biblioteca_enigma.egg-info/top_level.txt
enigma/__init__.py
enigma/biblioteca.py