Metadata-Version: 2.1
Name: biblioteca-enigma
Version: 0.0.1
Summary: Biblioteca enigma para aps de Algebra Linear
Author: Laura Pontiroli Machado
Author-email: laahpontiroli@gmail.com
License: MIT License
Keywords: enigma
License-File: LICENCE
Requires-Dist: numpy
